{"chunk_definitions":[{"row":8,"row_count":1,"visible":true,"expansion_state":0,"options":{"engine":"r","label":"Setup","include":false},"document_id":"EBC68C78","chunk_id":"csetup_chunk","chunk_label":"Setup"},{"row":26,"row_count":1,"visible":true,"expansion_state":0,"options":{"engine":"r","label":"Load Libraries"},"document_id":"EBC68C78","chunk_id":"cx8m1vvpjbsum","chunk_label":"Load Libraries"},{"row":277,"row_count":1,"visible":true,"expansion_state":0,"options":{"engine":"r","label":"plotly","fig.width":12,"fig.height":6},"document_id":"EBC68C78","chunk_id":"cjoqb2vou4ww7","chunk_label":"plotly"},{"row":300,"row_count":1,"visible":true,"expansion_state":0,"options":{"engine":"r","label":"tasting","fig.height":10,"fig.width":10},"document_id":"EBC68C78","chunk_id":"cyufq8pjgt0q7","chunk_label":"tasting"},{"row":325,"row_count":1,"visible":true,"expansion_state":0,"options":{"engine":"r","label":"unnamed-chunk-10"},"document_id":"EBC68C78","chunk_id":"c1s5k4ww9ip0r","chunk_label":"unnamed-chunk-5"}],"doc_write_time":1613257336}